vineyard/contrib/pyspark/__init__.py
vineyard/contrib/pyspark/pyspark.py
vineyard/contrib/pyspark/tests/__init__.py
vineyard/contrib/pyspark/tests/conftest.py
vineyard/contrib/pyspark/tests/test_pyspark.py
vineyard_pyspark-0.24.2.dist-info/LICENSE
vineyard_pyspark-0.24.2.dist-info/METADATA
vineyard_pyspark-0.24.2.dist-info/NOTICE.txt
vineyard_pyspark-0.24.2.dist-info/WHEEL
vineyard_pyspark-0.24.2.dist-info/top_level.txt
vineyard_pyspark-0.24.2.dist-info/RECORD
