Metadata-Version: 2.1
Name: vineyard-pyspark
Version: 0.24.2
Summary: Vineyard integration with PySpark
Home-page: https://v6d.io
Author: The vineyard team
Author-email: developers@v6d.io
License: Apache License 2.0
Project-URL: Documentation, https://v6d.io
Project-URL: Source, https://github.com/v6d-io/v6d
Project-URL: Tracker, https://github.com/v6d-io/v6d/issues
Platform: POSIX
Platform: MacOS
Classifier: Development Status :: 5 - Production/Stable
Classifier: Intended Audience :: Developers
Classifier: Intended Audience :: Science/Research
Classifier: License :: OSI Approved :: Apache Software License
Classifier: Topic :: Software Development :: Libraries
Classifier: Topic :: System :: Distributed Computing
Classifier: Operating System :: MacOS :: MacOS X
Classifier: Operating System :: POSIX
Classifier: Programming Language :: Python
Classifier: Programming Language :: Python :: 3
Classifier: Programming Language :: Python :: 3.6
Classifier: Programming Language :: Python :: 3.7
Classifier: Programming Language :: Python :: 3.8
Classifier: Programming Language :: Python :: 3.9
Classifier: Programming Language :: Python :: 3.10
Classifier: Programming Language :: Python :: 3.11
Requires-Dist: click (<8.1)
Requires-Dist: pyspark[complete]
Requires-Dist: vineyard
